{
  "id": "3696926",
  "title": "Thịt kho trứng thơm cay",
  "link": "https://vnexpress.net/doi-song-cooking-3696926.html",
  "description": "Chỉ là thịt kho trứng quen thuộc, nhưng bổ sung thêm vài gia vị ớt, tỏi, hành, món ăn sẽ có hương vị thơm ngon lạ.",
  "author": "",
  "imageUrl": "https://vcdn1-giadinh.vnecdn.net/2021/08/09/thit-kho-trung-3887-1515576615-9520-1628476397.jpg?w=680&h=0&q=100&dpr=1&fit=crop&s=39vXIcqPQUJ2hozvBFYJPQ",
  "prepTime": "",
  "servingSize": "",
  "calories": "",
  "ingredients": [],
  "steps": [],
  "tags": [
    "Xèo xèo"
  ],
  "createdAt": "2025-05-17T10:12:04.873Z"
}
